lovethedocs/__init__.py
lovethedocs/__main__.py
lovethedocs/ports.py
lovethedocs/application/__init__.py
lovethedocs/application/config.py
lovethedocs/application/diff_review.py
lovethedocs/application/logging_setup.py
lovethedocs/application/mappers.py
lovethedocs/application/utils.py
lovethedocs/application/pipeline/__init__.py
lovethedocs/application/pipeline/async_runner.py
lovethedocs/application/pipeline/factory.py
lovethedocs/application/pipeline/progress.py
lovethedocs/application/pipeline/summary.py
lovethedocs/application/pipeline/sync_runner.py
lovethedocs/cli/__init__.py
lovethedocs/cli/app.py
lovethedocs/domain/__init__.py
lovethedocs/domain/ports.py
lovethedocs/domain/docstyle/__init__.py
lovethedocs/domain/docstyle/base.py
lovethedocs/domain/docstyle/google_style.py
lovethedocs/domain/docstyle/numpy_style.py
lovethedocs/domain/models/__init__.py
lovethedocs/domain/models/edits.py
lovethedocs/domain/models/source_module.py
lovethedocs/domain/models/update_result.py
lovethedocs/domain/services/__init__.py
lovethedocs/domain/services/generator.py
lovethedocs/domain/services/patcher.py
lovethedocs/domain/services/prompt_builder.py
lovethedocs/domain/templates/__init__.py
lovethedocs/domain/templates/google.txt
lovethedocs/domain/templates/numpy.txt
lovethedocs/domain/templates/prompt_templates.py
lovethedocs/domain/use_cases/update_docs.py
lovethedocs/gateways/__init__.py
lovethedocs/gateways/diff_viewers.py
lovethedocs/gateways/lovethedocs_schema.json
lovethedocs/gateways/openai_client.py
lovethedocs/gateways/project_file_system.py
lovethedocs/gateways/schema_loader.py
lovethedocs-0.2.10.dist-info/licenses/LICENSE
lovethedocs-0.2.10.dist-info/METADATA
lovethedocs-0.2.10.dist-info/WHEEL
lovethedocs-0.2.10.dist-info/entry_points.txt
lovethedocs-0.2.10.dist-info/top_level.txt
lovethedocs-0.2.10.dist-info/RECORD
