Metadata-Version: 2.4
Name: lovethedocs
Version: 0.2.10
Summary: LLM-powered documentation tool
Author-email: Ian Davenport <davenport.ianc@gmail.com>
License-Expression: Apache-2.0
Project-URL: Homepage, https://github.com/davenpi/lovethedocs
Project-URL: Issues, https://github.com/davenpi/lovethedocs/issues
Classifier: Development Status :: 3 - Alpha
Classifier: Intended Audience :: Developers
Classifier: Natural Language :: English
Classifier: Programming Language :: Python :: 3.9
Classifier: Programming Language :: Python :: 3.10
Classifier: Programming Language :: Python :: 3.11
Classifier: Programming Language :: Python :: 3.12
Requires-Python: >=3.9
License-File: LICENSE
Requires-Dist: openai>=1.74.0
Requires-Dist: python-dotenv>=1.1.0
Requires-Dist: pydantic>=2.11.0
Requires-Dist: jsonschema>=4.0.0
Requires-Dist: libcst>=1.7.0
Requires-Dist: rich>=14.0.0
Requires-Dist: typer>=0.15.0
Provides-Extra: dev
Requires-Dist: pytest>=8.3.5; extra == "dev"
Dynamic: license-file
